{"nodes": [{"id": "frontend_src_pages_markets_tsx", "label": "Markets.tsx", "file_type": "code", "source_file": "frontend\\src\\pages\\Markets.tsx", "source_location": "L1"}, {"id": "markets_generatemockbars", "label": "generateMockBars()", "file_type": "code", "source_file": "frontend\\src\\pages\\Markets.tsx", "source_location": "L11"}], "edges": [{"source": "frontend_src_pages_markets_tsx", "target": "react", "relation": "imports_from", "confidence": "EXTRACTED", "source_file": "frontend\\src\\pages\\Markets.tsx", "source_location": "L1", "weight": 1.0}, {"source": "frontend_src_pages_markets_tsx", "target": "frontend_src_components_charts_candlestickchart", "relation": "imports_from", "confidence": "EXTRACTED", "source_file": "frontend\\src\\pages\\Markets.tsx", "source_location": "L2", "weight": 1.0}, {"source": "frontend_src_pages_markets_tsx", "target": "frontend_src_components_charts_heatmap", "relation": "imports_from", "confidence": "EXTRACTED", "source_file": "frontend\\src\\pages\\Markets.tsx", "source_location": "L3", "weight": 1.0}, {"source": "frontend_src_pages_markets_tsx", "target": "frontend_src_store_signals_store", "relation": "imports_from", "confidence": "EXTRACTED", "source_file": "frontend\\src\\pages\\Markets.tsx", "source_location": "L4", "weight": 1.0}, {"source": "frontend_src_pages_markets_tsx", "target": "frontend_src_types", "relation": "imports_from", "confidence": "EXTRACTED", "source_file": "frontend\\src\\pages\\Markets.tsx", "source_location": "L5", "weight": 1.0}, {"source": "frontend_src_pages_markets_tsx", "target": "markets_generatemockbars", "relation": "contains", "confidence": "EXTRACTED", "source_file": "frontend\\src\\pages\\Markets.tsx", "source_location": "L11", "weight": 1.0}], "raw_calls": [{"caller_nid": "markets_generatemockbars", "callee": "charCodeAt", "source_file": "frontend\\src\\pages\\Markets.tsx", "source_location": "L12"}, {"caller_nid": "markets_generatemockbars", "callee": "now", "source_file": "frontend\\src\\pages\\Markets.tsx", "source_location": "L19"}, {"caller_nid": "markets_generatemockbars", "callee": "random", "source_file": "frontend\\src\\pages\\Markets.tsx", "source_location": "L21"}, {"caller_nid": "markets_generatemockbars", "callee": "max", "source_file": "frontend\\src\\pages\\Markets.tsx", "source_location": "L22"}, {"caller_nid": "markets_generatemockbars", "callee": "push", "source_file": "frontend\\src\\pages\\Markets.tsx", "source_location": "L24"}, {"caller_nid": "markets_generatemockbars", "callee": "toISOString", "source_file": "frontend\\src\\pages\\Markets.tsx", "source_location": "L25"}, {"caller_nid": "markets_generatemockbars", "callee": "max", "source_file": "frontend\\src\\pages\\Markets.tsx", "source_location": "L27"}, {"caller_nid": "markets_generatemockbars", "callee": "random", "source_file": "frontend\\src\\pages\\Markets.tsx", "source_location": "L27"}, {"caller_nid": "markets_generatemockbars", "callee": "min", "source_file": "frontend\\src\\pages\\Markets.tsx", "source_location": "L28"}, {"caller_nid": "markets_generatemockbars", "callee": "random", "source_file": "frontend\\src\\pages\\Markets.tsx", "source_location": "L28"}, {"caller_nid": "markets_generatemockbars", "callee": "random", "source_file": "frontend\\src\\pages\\Markets.tsx", "source_location": "L30"}]}